admin_autocomplete/__init__.py
admin_autocomplete/admin.py
admin_autocomplete/apps.py
admin_autocomplete/static/admin_autocomplete/css/autocomplete.css
admin_autocomplete/static/admin_autocomplete/js/autocomplete.js
admin_autocomplete/templates/admin/change_list.html
admin_autocomplete/tests/__init__.py
admin_autocomplete/tests/test_e2e.py
admin_autocomplete/urls.py
admin_autocomplete/views.py
django_admin_autocomplete-0.2.1.dist-info/LICENSE
django_admin_autocomplete-0.2.1.dist-info/METADATA
django_admin_autocomplete-0.2.1.dist-info/WHEEL
django_admin_autocomplete-0.2.1.dist-info/RECORD
